kimi_code/__init__.py
kimi_code-1.5.dist-info/WHEEL
kimi_code-1.5.dist-info/entry_points.txt
kimi_code-1.5.dist-info/METADATA
kimi_code-1.5.dist-info/RECORD
