Metadata-Version: 2.3
Name: kimi-code
Version: 1.5
Summary: Kimi Code is a CLI agent that lives in your terminal.
Requires-Dist: kimi-cli==1.5
Requires-Python: >=3.12
